undetected_playwright/__init__.py
undetected_playwright/ninja.py
undetected_playwright/puppeteer-extra-plugin-stealth/evasions/_template/index.js
undetected_playwright/puppeteer-extra-plugin-stealth/evasions/_template/package.json
undetected_playwright/puppeteer-extra-plugin-stealth/evasions/_utils/index.js
undetected_playwright/puppeteer-extra-plugin-stealth/evasions/_utils/withUtils.js
undetected_playwright/puppeteer-extra-plugin-stealth/evasions/chrome.app/index.js
undetected_playwright/puppeteer-extra-plugin-stealth/evasions/chrome.app/package.json
undetected_playwright/puppeteer-extra-plugin-stealth/evasions/chrome.csi/index.js
undetected_playwright/puppeteer-extra-plugin-stealth/evasions/chrome.csi/package.json
undetected_playwright/puppeteer-extra-plugin-stealth/evasions/chrome.loadTimes/index.js
undetected_playwright/puppeteer-extra-plugin-stealth/evasions/chrome.loadTimes/package.json
undetected_playwright/puppeteer-extra-plugin-stealth/evasions/chrome.runtime/index.js
undetected_playwright/puppeteer-extra-plugin-stealth/evasions/chrome.runtime/package.json
undetected_playwright/puppeteer-extra-plugin-stealth/evasions/chrome.runtime/staticData.json
undetected_playwright/puppeteer-extra-plugin-stealth/evasions/defaultArgs/index.js
undetected_playwright/puppeteer-extra-plugin-stealth/evasions/defaultArgs/package.json
undetected_playwright/puppeteer-extra-plugin-stealth/evasions/iframe.contentWindow/index.js
undetected_playwright/puppeteer-extra-plugin-stealth/evasions/iframe.contentWindow/package.json
undetected_playwright/puppeteer-extra-plugin-stealth/evasions/media.codecs/index.js
undetected_playwright/puppeteer-extra-plugin-stealth/evasions/media.codecs/package.json
undetected_playwright/puppeteer-extra-plugin-stealth/evasions/navigator.hardwareConcurrency/index.js
undetected_playwright/puppeteer-extra-plugin-stealth/evasions/navigator.hardwareConcurrency/package.json
undetected_playwright-0.2.0.dist-info/LICENSE
undetected_playwright-0.2.0.dist-info/METADATA
undetected_playwright-0.2.0.dist-info/WHEEL
undetected_playwright-0.2.0.dist-info/RECORD
